{
  "version": "https://jsonfeed.org/version/1.1",
  "title": "Planet AI",
  "items": [
    {
      "id": "d62899e92230e2b0",
      "url": "https://lucijagregov.com/2017/04/02/support-vector-machine-svm/",
      "title": "Support Vector Machine (SVM)",
      "content_html": "\u003cp\u003eSupport Vector Machine is a supervised learning type of algorithm and its goal is to find the optimal hyperplane which separates clusters of data. In 1D we will have a line instead of a hyperplane and in 2D it will be a plane. In higher dimensions only, we call it a hyperplane. Suppose we have a data with some positive and some negative examples. How do we divide positive examples from the negative ones?\u003c/p\u003e\n\u003cp\u003e\u003cspan id=\"more-1152\"\u003e\u003c/span\u003e\u003c/p\u003e\n\u003cp\u003e\u003cdiv data-shortcode=\"caption\" id=\"attachment_1161\" style=\"width: 318px\" class=\"wp-caption aligncenter\"\u003e\u003cimg aria-describedby=\"caption-attachment-1161\" loading=\"lazy\" data-attachment-id=\"1161\" data-permalink=\"https://lucijagregov.com/2017/04/02/support-vector-machine-svm/svm/\" data-orig-file=\"https://lucijagregov.com/wp-content/uploads/2017/03/svm.png\" data-orig-size=\"308,257\" data-comments-opened=\"1\" data-image-meta=\"{\u0026quot;aperture\u0026quot;:\u0026quot;0\u0026quot;,\u0026quot;credit\u0026quot;:\u0026quot;\u0026quot;,\u0026quot;camera\u0026quot;:\u0026quot;\u0026quot;,\u0026quot;caption\u0026quot;:\u0026quot;\u0026quot;,\u0026quot;created_timestamp\u0026quot;:\u0026quot;0\u0026quot;,\u0026quot;copyright\u0026quot;:\u0026quot;\u0026quot;,\u0026quot;focal_length\u0026quot;:\u0026quot;0\u0026quot;,\u0026quot;iso\u0026quot;:\u0026quot;0\u0026quot;,\u0026quot;shutter_speed\u0026quot;:\u0026quot;0\u0026quot;,\u0026quot;title\u0026quot;:\u0026quot;\u0026quot;,\u0026quot;orientation\u0026quot;:\u0026quot;0\u0026quot;}\" data-image-title=\"svm\" data-image-description=\"\" data-image-caption=\"\" data-medium-file=\"https://lucijagregov.com/wp-content/uploads/2017/03/svm.png?w=300\" data-large-file=\"https://lucijagregov.com/wp-content/uploads/2017/03/svm.png?w=308\" class=\"alignnone size-full wp-image-1161 aligncenter\" src=\"https://lucijagregov.com/wp-content/uploads/2017/03/svm.png\" alt=\"svm\" width=\"308\" height=\"257\" srcset=\"https://lucijagregov.com/wp-content/uploads/2017/03/svm.png 308w, https://lucijagregov.com/wp-content/uploads/2017/03/svm.png?w=150\u0026amp;h=125 150w, https://lucijagregov.com/wp-content/uploads/2017/03/svm.png?w=300\u0026amp;h=250 300w\" sizes=\"(max-width: 308px) 100vw, 308px\" /\u003e\u003cp id=\"caption-attachment-1161\" class=\"wp-caption-text\"\u003eThe dataset with two clusters of positive (x) and negative (o) examples. Image is taken from http://cs229.stanford.edu/notes/cs229-notes3.pdf\u003c/p\u003e\u003c/div\u003e\u003c/p\u003e\n\u003cp\u003e\u003ca href=\"https://en.wikipedia.org/wiki/Vladimir_Vapnik\"\u003eVladimir Vapnik\u003c/a\u003e suggested drawing a straight line to separate them.  This is the simplest linear SVM for linearly separable data (not all data is linearly separable). The question that SVM is trying to answer is \u0026#8211; which straight line? There are (infinitely) many possibilities. In the figure above, we have three lines. The middle full line was our first and obvious choice and it is the best one. Our goal is to have the line which leaves as much space as possible from the boundaries. The widest margin we can get in our case is represented by two dotted lines. This is an optimization problem and I will explain the details and mathematics below. Then I will show how to implement it in Python.\u003c/p\u003e\n\u003cp\u003eHyperplane is the linear equation of the form\u003c/p\u003e\n\u003cp style=\"text-align:center;\"\u003e\u003cimg src=\"https://s0.wp.com/latex.php?latex=w_%7B1%7Dx_%7B1%7D+%2Bw_%7B2%7Dx_%7B2%7D+%2B+%5Ccdots+%2Bw_%7Bn%7Dx_%7Bn%7D+%3D+b\u0026#038;bg=ffffff\u0026#038;fg=000\u0026#038;s=0\u0026#038;c=20201002\" srcset=\"https://s0.wp.com/latex.php?latex=w_%7B1%7Dx_%7B1%7D+%2Bw_%7B2%7Dx_%7B2%7D+%2B+%5Ccdots+%2Bw_%7Bn%7Dx_%7Bn%7D+%3D+b\u0026#038;bg=ffffff\u0026#038;fg=000\u0026#038;s=0\u0026#038;c=20201002 1x, https://s0.wp.com/latex.php?latex=w_%7B1%7Dx_%7B1%7D+%2Bw_%7B2%7Dx_%7B2%7D+%2B+%5Ccdots+%2Bw_%7Bn%7Dx_%7Bn%7D+%3D+b\u0026#038;bg=ffffff\u0026#038;fg=000\u0026#038;s=0\u0026#038;c=20201002\u0026#038;zoom=4.5 4x\" alt=\"w_{1}x_{1} +w_{2}x_{2} + \u0026#92;cdots +w_{n}x_{n} = b\" class=\"latex\" /\u003e\u003c/p\u003e\n\u003cp style=\"text-align:left;\"\u003eIt separates the space into two half-spaces:\u003c/p\u003e\n\u003cp style=\"text-align:center;\"\u003e\u003cimg src=\"https://s0.wp.com/latex.php?latex=w_%7B1%7Dx_%7B1%7D+%2Bw_%7B2%7Dx_%7B2%7D+%2B+%5Ccdots+%2Bw_%7Bn%7Dx_%7Bn%7D+%3C+b\u0026#038;bg=ffffff\u0026#038;fg=000\u0026#038;s=0\u0026#038;c=20201002\" srcset=\"https://s0.wp.com/latex.php?latex=w_%7B1%7Dx_%7B1%7D+%2Bw_%7B2%7Dx_%7B2%7D+%2B+%5Ccdots+%2Bw_%7Bn%7Dx_%7Bn%7D+%3C+b\u0026#038;bg=ffffff\u0026#038;fg=000\u0026#038;s=0\u0026#038;c=20201002 1x, https://s0.wp.com/latex.php?latex=w_%7B1%7Dx_%7B1%7D+%2Bw_%7B2%7Dx_%7B2%7D+%2B+%5Ccdots+%2Bw_%7Bn%7Dx_%7Bn%7D+%3C+b\u0026#038;bg=ffffff\u0026#038;fg=000\u0026#038;s=0\u0026#038;c=20201002\u0026#038;zoom=4.5 4x\" alt=\"w_{1}x_{1} +w_{2}x_{2} + \u0026#92;cdots +w_{n}x_{n} \u0026lt; b\" class=\"latex\" /\u003e\u003c/p\u003e\n\u003cp style=\"text-align:left;\"\u003eand\u003c/p\u003e\n\u003cp style=\"text-align:center;\"\u003e\u003cimg src=\"https://s0.wp.com/latex.php?latex=w_%7B1%7Dx_%7B1%7D+%2Bw_%7B2%7Dx_%7B2%7D+%2B+%5Ccdots+%2Bw_%7Bn%7Dx_%7Bn%7D+%3E+b\u0026#038;bg=ffffff\u0026#038;fg=000\u0026#038;s=0\u0026#038;c=20201002\" srcset=\"https://s0.wp.com/latex.php?latex=w_%7B1%7Dx_%7B1%7D+%2Bw_%7B2%7Dx_%7B2%7D+%2B+%5Ccdots+%2Bw_%7Bn%7Dx_%7Bn%7D+%3E+b\u0026#038;bg=ffffff\u0026#038;fg=000\u0026#038;s=0\u0026#038;c=20201002 1x, https://s0.wp.com/latex.php?latex=w_%7B1%7Dx_%7B1%7D+%2Bw_%7B2%7Dx_%7B2%7D+%2B+%5Ccdots+%2Bw_%7Bn%7Dx_%7Bn%7D+%3E+b\u0026#038;bg=ffffff\u0026#038;fg=000\u0026#038;s=0\u0026#038;c=20201002\u0026#038;zoom=4.5 4x\" alt=\"w_{1}x_{1} +w_{2}x_{2} + \u0026#92;cdots +w_{n}x_{n} \u0026gt; b\" class=\"latex\" /\u003e\u003c/p\u003e\n\u003cp style=\"text-align:left;\"\u003eHyperplanes are used in many other machine learning algorithms, such as decision trees to define decision boundaries.\u003c/p\u003e\n\u003cp style=\"text-align:left;\"\u003eWe can write the hyperplane formula in the form\u003c/p\u003e\n\u003cp style=\"text-align:center;\"\u003e\u003cimg src=\"https://s0.wp.com/latex.php?latex=y%28x%29+%3D+%5Csum_%7Bi%3D1%7D%5E%7Bn%7Dw_%7Bi%7Dx_%7Bi%7D+%2B+b+%3D+w%5E%7B%5Ctau%7Dx%C2%A0%2B+b+%5Cquad+%281%29\u0026#038;bg=ffffff\u0026#038;fg=000\u0026#038;s=0\u0026#038;c=20201002\" srcset=\"https://s0.wp.com/latex.php?latex=y%28x%29+%3D+%5Csum_%7Bi%3D1%7D%5E%7Bn%7Dw_%7Bi%7Dx_%7Bi%7D+%2B+b+%3D+w%5E%7B%5Ctau%7Dx%C2%A0%2B+b+%5Cquad+%281%29\u0026#038;bg=ffffff\u0026#038;fg=000\u0026#038;s=0\u0026#038;c=20201002 1x, https://s0.wp.com/latex.php?latex=y%28x%29+%3D+%5Csum_%7Bi%3D1%7D%5E%7Bn%7Dw_%7Bi%7Dx_%7Bi%7D+%2B+b+%3D+w%5E%7B%5Ctau%7Dx%C2%A0%2B+b+%5Cquad+%281%29\u0026#038;bg=ffffff\u0026#038;fg=000\u0026#038;s=0\u0026#038;c=20201002\u0026#038;zoom=4.5 4x\" alt=\"y(x) = \u0026#92;sum_{i=1}^{n}w_{i}x_{i} + b = w^{\u0026#92;tau}x + b \u0026#92;quad (1)\" class=\"latex\" /\u003e\u003c/p\u003e\n\u003cp\u003ewhere vector w is perpendicular to the hyperplane (analogous to the middle full line in the picture above for 2D space) and b is the distance from the origin. We call it the parameters vector or the vector of weights.\u003c/p\u003e\n\u003cp\u003eIn terms of positive and negative samples, formula (1) means that we are taking the dot product of a vector x to the normal vector w, in order to determine whether x belongs to the positive or negative sample (we need to classify it).\u003c/p\u003e\n\u003cp\u003eLooking at the formula (1) we can see that the middle line equation (which represents the decision boundary) looks like\u003c/p\u003e\n\u003cp style=\"text-align:center;\"\u003e\u003cimg src=\"https://s0.wp.com/latex.php?latex=w%5E%7B%5Ctau%7Dx%C2%A0%2B+b+%3D+0\u0026#038;bg=ffffff\u0026#038;fg=000\u0026#038;s=0\u0026#038;c=20201002\" srcset=\"https://s0.wp.com/latex.php?latex=w%5E%7B%5Ctau%7Dx%C2%A0%2B+b+%3D+0\u0026#038;bg=ffffff\u0026#038;fg=000\u0026#038;s=0\u0026#038;c=20201002 1x, https://s0.wp.com/latex.php?latex=w%5E%7B%5Ctau%7Dx%C2%A0%2B+b+%3D+0\u0026#038;bg=ffffff\u0026#038;fg=000\u0026#038;s=0\u0026#038;c=20201002\u0026#038;zoom=4.5 4x\" alt=\"w^{\u0026#92;tau}x + b = 0\" class=\"latex\" /\u003e\u003c/p\u003e\n\u003cp style=\"text-align:left;\"\u003eAccordingly, if we say that positive and negative samples belong to the set\u003c/p\u003e\n\u003cp style=\"text-align:center;\"\u003e\u003cimg src=\"https://s0.wp.com/latex.php?latex=y_%7Bi%7D+%3D+%5C%7B%2B1%2C+-1+%5C%7D%2C+i+%3D+1%2C+%5Ccdots%2C+n\u0026#038;bg=ffffff\u0026#038;fg=000\u0026#038;s=0\u0026#038;c=20201002\" srcset=\"https://s0.wp.com/latex.php?latex=y_%7Bi%7D+%3D+%5C%7B%2B1%2C+-1+%5C%7D%2C+i+%3D+1%2C+%5Ccdots%2C+n\u0026#038;bg=ffffff\u0026#038;fg=000\u0026#038;s=0\u0026#038;c=20201002 1x, https://s0.wp.com/latex.php?latex=y_%7Bi%7D+%3D+%5C%7B%2B1%2C+-1+%5C%7D%2C+i+%3D+1%2C+%5Ccdots%2C+n\u0026#038;bg=ffffff\u0026#038;fg=000\u0026#038;s=0\u0026#038;c=20201002\u0026#038;zoom=4.5 4x\" alt=\"y_{i} = \u0026#92;{+1, -1 \u0026#92;}, i = 1, \u0026#92;cdots, n\" class=\"latex\" /\u003e\u003c/p\u003e\n\u003cp style=\"text-align:left;\"\u003ethen  the equations for the support vector lines which represent positive (+1) and negative (-1) examples are given by\u003c/p\u003e\n\u003cp style=\"text-align:center;\"\u003e\u003cimg src=\"https://s0.wp.com/latex.php?latex=%C2%A0w%5E%7B%5Ctau%7Dx%C2%A0%2B+b+%5Cgeq+1\u0026#038;bg=ffffff\u0026#038;fg=000\u0026#038;s=0\u0026#038;c=20201002\" srcset=\"https://s0.wp.com/latex.php?latex=%C2%A0w%5E%7B%5Ctau%7Dx%C2%A0%2B+b+%5Cgeq+1\u0026#038;bg=ffffff\u0026#038;fg=000\u0026#038;s=0\u0026#038;c=20201002 1x, https://s0.wp.com/latex.php?latex=%C2%A0w%5E%7B%5Ctau%7Dx%C2%A0%2B+b+%5Cgeq+1\u0026#038;bg=ffffff\u0026#038;fg=000\u0026#038;s=0\u0026#038;c=20201002\u0026#038;zoom=4.5 4x\" alt=\" w^{\u0026#92;tau}x + b \u0026#92;geq 1\" class=\"latex\" /\u003e\u003c/p\u003e\n\u003cp style=\"text-align:center;\"\u003e\u003cimg src=\"https://s0.wp.com/latex.php?latex=%C2%A0w%5E%7B%5Ctau%7Dx%C2%A0%2B+b+%5Cleq+-1\u0026#038;bg=ffffff\u0026#038;fg=000\u0026#038;s=0\u0026#038;c=20201002\" srcset=\"https://s0.wp.com/latex.php?latex=%C2%A0w%5E%7B%5Ctau%7Dx%C2%A0%2B+b+%5Cleq+-1\u0026#038;bg=ffffff\u0026#038;fg=000\u0026#038;s=0\u0026#038;c=20201002 1x, https://s0.wp.com/latex.php?latex=%C2%A0w%5E%7B%5Ctau%7Dx%C2%A0%2B+b+%5Cleq+-1\u0026#038;bg=ffffff\u0026#038;fg=000\u0026#038;s=0\u0026#038;c=20201002\u0026#038;zoom=4.5 4x\" alt=\" w^{\u0026#92;tau}x + b \u0026#92;leq -1\" class=\"latex\" /\u003e\u003c/p\u003e\n\u003cp style=\"text-align:left;\"\u003eIf we multiply the equations above with \u003cimg src=\"https://s0.wp.com/latex.php?latex=y_%7Bi%7D\u0026#038;bg=ffffff\u0026#038;fg=000\u0026#038;s=0\u0026#038;c=20201002\" srcset=\"https://s0.wp.com/latex.php?latex=y_%7Bi%7D\u0026#038;bg=ffffff\u0026#038;fg=000\u0026#038;s=0\u0026#038;c=20201002 1x, https://s0.wp.com/latex.php?latex=y_%7Bi%7D\u0026#038;bg=ffffff\u0026#038;fg=000\u0026#038;s=0\u0026#038;c=20201002\u0026#038;zoom=4.5 4x\" alt=\"y_{i}\" class=\"latex\" /\u003e, for the middle line we get\u003c/p\u003e\n\u003cp style=\"text-align:center;\"\u003e\u003cimg src=\"https://s0.wp.com/latex.php?latex=%C2%A0y_%7Bi%7D%28w%5E%7B%5Ctau%7Dx_%7Bi%7D+%2B+b%29+-+1+%3D+0+%5Cquad+%282%29\u0026#038;bg=ffffff\u0026#038;fg=000\u0026#038;s=0\u0026#038;c=20201002\" srcset=\"https://s0.wp.com/latex.php?latex=%C2%A0y_%7Bi%7D%28w%5E%7B%5Ctau%7Dx_%7Bi%7D+%2B+b%29+-+1+%3D+0+%5Cquad+%282%29\u0026#038;bg=ffffff\u0026#038;fg=000\u0026#038;s=0\u0026#038;c=20201002 1x, https://s0.wp.com/latex.php?latex=%C2%A0y_%7Bi%7D%28w%5E%7B%5Ctau%7Dx_%7Bi%7D+%2B+b%29+-+1+%3D+0+%5Cquad+%282%29\u0026#038;bg=ffffff\u0026#038;fg=000\u0026#038;s=0\u0026#038;c=20201002\u0026#038;zoom=4.5 4x\" alt=\" y_{i}(w^{\u0026#92;tau}x_{i} + b) - 1 = 0 \u0026#92;quad (2)\" class=\"latex\" /\u003e\u003c/p\u003e\n\u003cp style=\"text-align:left;\"\u003eNow, we want to determine the width between the support vector hyperplanes. We can do that using the dot product between the difference of the two vectors pointing to the support points and the unit vector. This unit vector will be w divided by the magnitude of w. If we mark the vector to the positive sample with \u003cimg src=\"https://s0.wp.com/latex.php?latex=x_%7B%2B%7D\u0026#038;bg=ffffff\u0026#038;fg=000\u0026#038;s=0\u0026#038;c=20201002\" srcset=\"https://s0.wp.com/latex.php?latex=x_%7B%2B%7D\u0026#038;bg=ffffff\u0026#038;fg=000\u0026#038;s=0\u0026#038;c=20201002 1x, https://s0.wp.com/latex.php?latex=x_%7B%2B%7D\u0026#038;bg=ffffff\u0026#038;fg=000\u0026#038;s=0\u0026#038;c=20201002\u0026#038;zoom=4.5 4x\" alt=\"x_{+}\" class=\"latex\" /\u003e and the vector to the point that belongs in the negative sample \u003cimg src=\"https://s0.wp.com/latex.php?latex=x_%7B-%7D\u0026#038;bg=ffffff\u0026#038;fg=000\u0026#038;s=0\u0026#038;c=20201002\" srcset=\"https://s0.wp.com/latex.php?latex=x_%7B-%7D\u0026#038;bg=ffffff\u0026#038;fg=000\u0026#038;s=0\u0026#038;c=20201002 1x, https://s0.wp.com/latex.php?latex=x_%7B-%7D\u0026#038;bg=ffffff\u0026#038;fg=000\u0026#038;s=0\u0026#038;c=20201002\u0026#038;zoom=4.5 4x\" alt=\"x_{-}\" class=\"latex\" /\u003e, we can write\u003c/p\u003e\n\u003cp style=\"text-align:center;\"\u003e\u003cimg src=\"https://s0.wp.com/latex.php?latex=%5Ctext%7Bwidth%7D+%3D+%28x_%7B%2B%7D+-x_%7B-%7D%29+%5Cfrac%7Bw%7D%7B%5C%7Cw%5C%7C%7D+%5Cquad+%283%29\u0026#038;bg=ffffff\u0026#038;fg=000\u0026#038;s=0\u0026#038;c=20201002\" srcset=\"https://s0.wp.com/latex.php?latex=%5Ctext%7Bwidth%7D+%3D+%28x_%7B%2B%7D+-x_%7B-%7D%29+%5Cfrac%7Bw%7D%7B%5C%7Cw%5C%7C%7D+%5Cquad+%283%29\u0026#038;bg=ffffff\u0026#038;fg=000\u0026#038;s=0\u0026#038;c=20201002 1x, https://s0.wp.com/latex.php?latex=%5Ctext%7Bwidth%7D+%3D+%28x_%7B%2B%7D+-x_%7B-%7D%29+%5Cfrac%7Bw%7D%7B%5C%7Cw%5C%7C%7D+%5Cquad+%283%29\u0026#038;bg=ffffff\u0026#038;fg=000\u0026#038;s=0\u0026#038;c=20201002\u0026#038;zoom=4.5 4x\" alt=\"\u0026#92;text{width} = (x_{+} -x_{-}) \u0026#92;frac{w}{\u0026#92;|w\u0026#92;|} \u0026#92;quad (3)\" class=\"latex\" /\u003e\u003c/p\u003e\n\u003cp style=\"text-align:left;\"\u003eInserting values from (2) into (3) we get\u003c/p\u003e\n\u003cp style=\"text-align:center;\"\u003e \u003cimg src=\"https://s0.wp.com/latex.php?latex=%281-b+%2B+1%2Bb%29+%5Cfrac%7Bw%7D%7B%5C%7Cw%5C%7C%7D+%3D%5Cfrac%7B2%7D%7B%5C%7Cw%5C%7C%7D+%5Cquad+%284%29\u0026#038;bg=ffffff\u0026#038;fg=000\u0026#038;s=0\u0026#038;c=20201002\" srcset=\"https://s0.wp.com/latex.php?latex=%281-b+%2B+1%2Bb%29+%5Cfrac%7Bw%7D%7B%5C%7Cw%5C%7C%7D+%3D%5Cfrac%7B2%7D%7B%5C%7Cw%5C%7C%7D+%5Cquad+%284%29\u0026#038;bg=ffffff\u0026#038;fg=000\u0026#038;s=0\u0026#038;c=20201002 1x, https://s0.wp.com/latex.php?latex=%281-b+%2B+1%2Bb%29+%5Cfrac%7Bw%7D%7B%5C%7Cw%5C%7C%7D+%3D%5Cfrac%7B2%7D%7B%5C%7Cw%5C%7C%7D+%5Cquad+%284%29\u0026#038;bg=ffffff\u0026#038;fg=000\u0026#038;s=0\u0026#038;c=20201002\u0026#038;zoom=4.5 4x\" alt=\"(1-b + 1+b) \u0026#92;frac{w}{\u0026#92;|w\u0026#92;|} =\u0026#92;frac{2}{\u0026#92;|w\u0026#92;|} \u0026#92;quad (4)\" class=\"latex\" /\u003e\u003c/p\u003e\n\u003cp style=\"text-align:left;\"\u003ewhich is the length between the two support vector lines and we want to maximize it. So, what we want to do is\u003c/p\u003e\n\u003cp style=\"text-align:center;\"\u003e\u003cimg src=\"https://s0.wp.com/latex.php?latex=max+%5Cfrac%7B2%7D%7B%5C%7Cw%5C%7C%7D+%5Cto+%C2%A0max+%5Cfrac%7B1%7D%7B%5C%7Cw%5C%7C%7D\u0026#038;bg=ffffff\u0026#038;fg=000\u0026#038;s=0\u0026#038;c=20201002\" srcset=\"https://s0.wp.com/latex.php?latex=max+%5Cfrac%7B2%7D%7B%5C%7Cw%5C%7C%7D+%5Cto+%C2%A0max+%5Cfrac%7B1%7D%7B%5C%7Cw%5C%7C%7D\u0026#038;bg=ffffff\u0026#038;fg=000\u0026#038;s=0\u0026#038;c=20201002 1x, https://s0.wp.com/latex.php?latex=max+%5Cfrac%7B2%7D%7B%5C%7Cw%5C%7C%7D+%5Cto+%C2%A0max+%5Cfrac%7B1%7D%7B%5C%7Cw%5C%7C%7D\u0026#038;bg=ffffff\u0026#038;fg=000\u0026#038;s=0\u0026#038;c=20201002\u0026#038;zoom=4.5 4x\" alt=\"max \u0026#92;frac{2}{\u0026#92;|w\u0026#92;|} \u0026#92;to  max \u0026#92;frac{1}{\u0026#92;|w\u0026#92;|}\" class=\"latex\" /\u003e\u003c/p\u003e\n\u003cp style=\"text-align:left;\"\u003eor equivalently\u003c/p\u003e\n\u003cp style=\"text-align:center;\"\u003e\u003cimg src=\"https://s0.wp.com/latex.php?latex=min+%5Cfrac%7B1%7D%7B2%7D%5C%7Cw%5C%7C%5E2\u0026#038;bg=ffffff\u0026#038;fg=000\u0026#038;s=0\u0026#038;c=20201002\" srcset=\"https://s0.wp.com/latex.php?latex=min+%5Cfrac%7B1%7D%7B2%7D%5C%7Cw%5C%7C%5E2\u0026#038;bg=ffffff\u0026#038;fg=000\u0026#038;s=0\u0026#038;c=20201002 1x, https://s0.wp.com/latex.php?latex=min+%5Cfrac%7B1%7D%7B2%7D%5C%7Cw%5C%7C%5E2\u0026#038;bg=ffffff\u0026#038;fg=000\u0026#038;s=0\u0026#038;c=20201002\u0026#038;zoom=4.5 4x\" alt=\"min \u0026#92;frac{1}{2}\u0026#92;|w\u0026#92;|^2\" class=\"latex\" /\u003e\u003c/p\u003e\n\u003cp style=\"text-align:left;\"\u003esubject to the vector w. This is a quadratic optimization problem with linear constraints and to solve it we can use \u003ca href=\"https://en.wikipedia.org/wiki/Lagrange_multiplier\"\u003eLagrange multipliers\u003c/a\u003e. Since it is quadratic, it is convex with a single minimum. This is not the case, for example in neural networks.\u003c/p\u003e\n\u003cp style=\"text-align:left;\"\u003eIn general, we have some function\u003c/p\u003e\n\u003cp style=\"text-align:center;\"\u003e\u003cimg src=\"https://s0.wp.com/latex.php?latex=f%28x_%7B1%7D%2C+x_%7B2%7D%2C+%5Ccdots%2C+x_%7Bn%7D%29+%3A+%5Cmathbb%7BR%7D%5E%7Bn%7D+%5Cto+%5Cmathbb%7BR%7D\u0026#038;bg=ffffff\u0026#038;fg=000\u0026#038;s=0\u0026#038;c=20201002\" srcset=\"https://s0.wp.com/latex.php?latex=f%28x_%7B1%7D%2C+x_%7B2%7D%2C+%5Ccdots%2C+x_%7Bn%7D%29+%3A+%5Cmathbb%7BR%7D%5E%7Bn%7D+%5Cto+%5Cmathbb%7BR%7D\u0026#038;bg=ffffff\u0026#038;fg=000\u0026#038;s=0\u0026#038;c=20201002 1x, https://s0.wp.com/latex.php?latex=f%28x_%7B1%7D%2C+x_%7B2%7D%2C+%5Ccdots%2C+x_%7Bn%7D%29+%3A+%5Cmathbb%7BR%7D%5E%7Bn%7D+%5Cto+%5Cmathbb%7BR%7D\u0026#038;bg=ffffff\u0026#038;fg=000\u0026#038;s=0\u0026#038;c=20201002\u0026#038;zoom=4.5 4x\" alt=\"f(x_{1}, x_{2}, \u0026#92;cdots, x_{n}) : \u0026#92;mathbb{R}^{n} \u0026#92;to \u0026#92;mathbb{R}\" class=\"latex\" /\u003e\u003c/p\u003e\n\u003cp style=\"text-align:left;\"\u003eand we want to optimize f, while contraining it with function g\u003c/p\u003e\n\u003cp style=\"text-align:center;\"\u003e\u003cimg src=\"https://s0.wp.com/latex.php?latex=g%28x_%7B1%7D%2C+x_%7B2%7D%2C+%5Ccdots%2C+x_%7Bn%7D%29+%3D+0\u0026#038;bg=ffffff\u0026#038;fg=000\u0026#038;s=0\u0026#038;c=20201002\" srcset=\"https://s0.wp.com/latex.php?latex=g%28x_%7B1%7D%2C+x_%7B2%7D%2C+%5Ccdots%2C+x_%7Bn%7D%29+%3D+0\u0026#038;bg=ffffff\u0026#038;fg=000\u0026#038;s=0\u0026#038;c=20201002 1x, https://s0.wp.com/latex.php?latex=g%28x_%7B1%7D%2C+x_%7B2%7D%2C+%5Ccdots%2C+x_%7Bn%7D%29+%3D+0\u0026#038;bg=ffffff\u0026#038;fg=000\u0026#038;s=0\u0026#038;c=20201002\u0026#038;zoom=4.5 4x\" alt=\"g(x_{1}, x_{2}, \u0026#92;cdots, x_{n}) = 0\" class=\"latex\" /\u003e\u003c/p\u003e\n\u003cp style=\"text-align:left;\"\u003eThe main equation that we use with Lagrangian multipliers is\u003c/p\u003e\n\u003cp style=\"text-align:center;\"\u003e\u003cimg src=\"https://s0.wp.com/latex.php?latex=%5Cnabla+f%28x%29+%3D+%5Calpha+%5Cnabla+g%28x%29\u0026#038;bg=ffffff\u0026#038;fg=000\u0026#038;s=0\u0026#038;c=20201002\" srcset=\"https://s0.wp.com/latex.php?latex=%5Cnabla+f%28x%29+%3D+%5Calpha+%5Cnabla+g%28x%29\u0026#038;bg=ffffff\u0026#038;fg=000\u0026#038;s=0\u0026#038;c=20201002 1x, https://s0.wp.com/latex.php?latex=%5Cnabla+f%28x%29+%3D+%5Calpha+%5Cnabla+g%28x%29\u0026#038;bg=ffffff\u0026#038;fg=000\u0026#038;s=0\u0026#038;c=20201002\u0026#038;zoom=4.5 4x\" alt=\"\u0026#92;nabla f(x) = \u0026#92;alpha \u0026#92;nabla g(x)\" class=\"latex\" /\u003e\u003c/p\u003e\n\u003cp style=\"text-align:left;\"\u003eThe Lagrangian function is then\u003c/p\u003e\n\u003cp style=\"text-align:center;\"\u003e\u003cimg src=\"https://s0.wp.com/latex.php?latex=L%28x%2C+%5Calpha%29+%3D+f%28x%29+-+%5Calpha+g%28x%29\u0026#038;bg=ffffff\u0026#038;fg=000\u0026#038;s=0\u0026#038;c=20201002\" srcset=\"https://s0.wp.com/latex.php?latex=L%28x%2C+%5Calpha%29+%3D+f%28x%29+-+%5Calpha+g%28x%29\u0026#038;bg=ffffff\u0026#038;fg=000\u0026#038;s=0\u0026#038;c=20201002 1x, https://s0.wp.com/latex.php?latex=L%28x%2C+%5Calpha%29+%3D+f%28x%29+-+%5Calpha+g%28x%29\u0026#038;bg=ffffff\u0026#038;fg=000\u0026#038;s=0\u0026#038;c=20201002\u0026#038;zoom=4.5 4x\" alt=\"L(x, \u0026#92;alpha) = f(x) - \u0026#92;alpha g(x)\" class=\"latex\" /\u003e\u003c/p\u003e\n\u003cp style=\"text-align:left;\"\u003eUsing this equation, we look for points where\u003c/p\u003e\n\u003cp style=\"text-align:center;\"\u003e\u003cimg src=\"https://s0.wp.com/latex.php?latex=%5Cnabla+L%28x%2C+%5Calpha%29+%3D+0\u0026#038;bg=ffffff\u0026#038;fg=000\u0026#038;s=0\u0026#038;c=20201002\" srcset=\"https://s0.wp.com/latex.php?latex=%5Cnabla+L%28x%2C+%5Calpha%29+%3D+0\u0026#038;bg=ffffff\u0026#038;fg=000\u0026#038;s=0\u0026#038;c=20201002 1x, https://s0.wp.com/latex.php?latex=%5Cnabla+L%28x%2C+%5Calpha%29+%3D+0\u0026#038;bg=ffffff\u0026#038;fg=000\u0026#038;s=0\u0026#038;c=20201002\u0026#038;zoom=4.5 4x\" alt=\"\u0026#92;nabla L(x, \u0026#92;alpha) = 0\" class=\"latex\" /\u003e\u003c/p\u003e\n\u003cp style=\"text-align:left;\"\u003eIn our case, the Lagrangian function is\u003c/p\u003e\n\u003cp style=\"text-align:center;\"\u003e\u003cimg src=\"https://s0.wp.com/latex.php?latex=L%28w%2C+b%2C+%5Calpha%29+%3D%C2%A0%5Cfrac%7B1%7D%7B2%7D+%5C%7Cw%5C%7C%5E2+-+%5Csum_%7Bi%7D+%5Calpha_%7Bi%7D+%5B+y_%7Bi%7D%28w+x_%7Bi%7D+%2B+b%29+-+1+%5D+%5Cquad+%285%29\u0026#038;bg=ffffff\u0026#038;fg=000\u0026#038;s=0\u0026#038;c=20201002\" srcset=\"https://s0.wp.com/latex.php?latex=L%28w%2C+b%2C+%5Calpha%29+%3D%C2%A0%5Cfrac%7B1%7D%7B2%7D+%5C%7Cw%5C%7C%5E2+-+%5Csum_%7Bi%7D+%5Calpha_%7Bi%7D+%5B+y_%7Bi%7D%28w+x_%7Bi%7D+%2B+b%29+-+1+%5D+%5Cquad+%285%29\u0026#038;bg=ffffff\u0026#038;fg=000\u0026#038;s=0\u0026#038;c=20201002 1x, https://s0.wp.com/latex.php?latex=L%28w%2C+b%2C+%5Calpha%29+%3D%C2%A0%5Cfrac%7B1%7D%7B2%7D+%5C%7Cw%5C%7C%5E2+-+%5Csum_%7Bi%7D+%5Calpha_%7Bi%7D+%5B+y_%7Bi%7D%28w+x_%7Bi%7D+%2B+b%29+-+1+%5D+%5Cquad+%285%29\u0026#038;bg=ffffff\u0026#038;fg=000\u0026#038;s=0\u0026#038;c=20201002\u0026#038;zoom=4.5 4x\" alt=\"L(w, b, \u0026#92;alpha) = \u0026#92;frac{1}{2} \u0026#92;|w\u0026#92;|^2 - \u0026#92;sum_{i} \u0026#92;alpha_{i} [ y_{i}(w x_{i} + b) - 1 ] \u0026#92;quad (5)\" class=\"latex\" /\u003e\u003c/p\u003e\n\u003cp style=\"text-align:left;\"\u003eTaking partial derivatives, we get\u003c/p\u003e\n\u003cp style=\"text-align:center;\"\u003e\u003cimg src=\"https://s0.wp.com/latex.php?latex=%5Cfrac%7B%5Cpartial+L%7D%7B%5Cpartial+w%7D+%3D+w+-+%5Csum_%7Bi%7D+%5Calpha_%7Bi%7D+y_%7Bi%7D+x_%7Bi%7D+%3D+0\u0026#038;bg=ffffff\u0026#038;fg=000\u0026#038;s=0\u0026#038;c=20201002\" srcset=\"https://s0.wp.com/latex.php?latex=%5Cfrac%7B%5Cpartial+L%7D%7B%5Cpartial+w%7D+%3D+w+-+%5Csum_%7Bi%7D+%5Calpha_%7Bi%7D+y_%7Bi%7D+x_%7Bi%7D+%3D+0\u0026#038;bg=ffffff\u0026#038;fg=000\u0026#038;s=0\u0026#038;c=20201002 1x, https://s0.wp.com/latex.php?latex=%5Cfrac%7B%5Cpartial+L%7D%7B%5Cpartial+w%7D+%3D+w+-+%5Csum_%7Bi%7D+%5Calpha_%7Bi%7D+y_%7Bi%7D+x_%7Bi%7D+%3D+0\u0026#038;bg=ffffff\u0026#038;fg=000\u0026#038;s=0\u0026#038;c=20201002\u0026#038;zoom=4.5 4x\" alt=\"\u0026#92;frac{\u0026#92;partial L}{\u0026#92;partial w} = w - \u0026#92;sum_{i} \u0026#92;alpha_{i} y_{i} x_{i} = 0\" class=\"latex\" /\u003e\u003c/p\u003e\n\u003cp style=\"text-align:left;\"\u003eFrom there follows\u003c/p\u003e\n\u003cp style=\"text-align:center;\"\u003e\u003cimg src=\"https://s0.wp.com/latex.php?latex=w+%3D+%5Csum_%7Bi%7D+%5Calpha_%7Bi%7D+y_%7Bi%7D+x_%7Bi%7D\u0026#038;bg=ffffff\u0026#038;fg=000\u0026#038;s=0\u0026#038;c=20201002\" srcset=\"https://s0.wp.com/latex.php?latex=w+%3D+%5Csum_%7Bi%7D+%5Calpha_%7Bi%7D+y_%7Bi%7D+x_%7Bi%7D\u0026#038;bg=ffffff\u0026#038;fg=000\u0026#038;s=0\u0026#038;c=20201002 1x, https://s0.wp.com/latex.php?latex=w+%3D+%5Csum_%7Bi%7D+%5Calpha_%7Bi%7D+y_%7Bi%7D+x_%7Bi%7D\u0026#038;bg=ffffff\u0026#038;fg=000\u0026#038;s=0\u0026#038;c=20201002\u0026#038;zoom=4.5 4x\" alt=\"w = \u0026#92;sum_{i} \u0026#92;alpha_{i} y_{i} x_{i}\" class=\"latex\" /\u003e\u003c/p\u003e\n\u003cp style=\"text-align:left;\"\u003eNow taking the partial derivative over b,\u003c/p\u003e\n\u003cp style=\"text-align:center;\"\u003e\u003cimg src=\"https://s0.wp.com/latex.php?latex=%5Cfrac%7B%5Cpartial+L%7D%7B%5Cpartial+b%7D+%3D+-+%5Csum_%7Bi%7D+%5Calpha_%7Bi%7D+y_%7Bi%7D+%3D+0\u0026#038;bg=ffffff\u0026#038;fg=000\u0026#038;s=0\u0026#038;c=20201002\" srcset=\"https://s0.wp.com/latex.php?latex=%5Cfrac%7B%5Cpartial+L%7D%7B%5Cpartial+b%7D+%3D+-+%5Csum_%7Bi%7D+%5Calpha_%7Bi%7D+y_%7Bi%7D+%3D+0\u0026#038;bg=ffffff\u0026#038;fg=000\u0026#038;s=0\u0026#038;c=20201002 1x, https://s0.wp.com/latex.php?latex=%5Cfrac%7B%5Cpartial+L%7D%7B%5Cpartial+b%7D+%3D+-+%5Csum_%7Bi%7D+%5Calpha_%7Bi%7D+y_%7Bi%7D+%3D+0\u0026#038;bg=ffffff\u0026#038;fg=000\u0026#038;s=0\u0026#038;c=20201002\u0026#038;zoom=4.5 4x\" alt=\"\u0026#92;frac{\u0026#92;partial L}{\u0026#92;partial b} = - \u0026#92;sum_{i} \u0026#92;alpha_{i} y_{i} = 0\" class=\"latex\" /\u003e\u003c/p\u003e\n\u003cp style=\"text-align:left;\"\u003eThis gives us\u003c/p\u003e\n\u003cp style=\"text-align:center;\"\u003e\u003cimg src=\"https://s0.wp.com/latex.php?latex=%5Csum_%7Bi%7D+%5Calpha_%7Bi%7D+y_%7Bi%7D+%3D+0\u0026#038;bg=ffffff\u0026#038;fg=000\u0026#038;s=0\u0026#038;c=20201002\" srcset=\"https://s0.wp.com/latex.php?latex=%5Csum_%7Bi%7D+%5Calpha_%7Bi%7D+y_%7Bi%7D+%3D+0\u0026#038;bg=ffffff\u0026#038;fg=000\u0026#038;s=0\u0026#038;c=20201002 1x, https://s0.wp.com/latex.php?latex=%5Csum_%7Bi%7D+%5Calpha_%7Bi%7D+y_%7Bi%7D+%3D+0\u0026#038;bg=ffffff\u0026#038;fg=000\u0026#038;s=0\u0026#038;c=20201002\u0026#038;zoom=4.5 4x\" alt=\"\u0026#92;sum_{i} \u0026#92;alpha_{i} y_{i} = 0\" class=\"latex\" /\u003e\u003c/p\u003e\n\u003cp style=\"text-align:left;\"\u003eSubstituting w back into (5) leads to\u003c/p\u003e\n\u003cp style=\"text-align:center;\"\u003e\u003cimg src=\"https://s0.wp.com/latex.php?latex=L%28w%2C+b%2C+%5Calpha%29+%3D+%5Cfrac%7B1%7D%7B2%7D+%28%5Csum_%7Bi%7D+%5Calpha_%7Bi%7D+y_%7Bi%7D+x_%7Bi%7D%29%28%5Csum_%7Bj%7D+%5Calpha_%7Bj%7D+y_%7Bj%7D+x_%7Bj%7D%29+-+%28%5Csum_%7Bi%7D%5Calpha_%7Bi%7D+y_%7Bi%7D+x_%7Bi%7D%29%28%5Csum_%7Bj%7D+%5Calpha_%7Bj%7D+y_%7Bj%7D+x_%7Bj%7D%29+-+%5Csum_%7Bi%7D+%5Calpha_%7Bi%7D+y_%7Bi%7D+%2B+%5Csum_%7Bi%7D+%5Calpha_%7Bi%7D\u0026#038;bg=ffffff\u0026#038;fg=000\u0026#038;s=0\u0026#038;c=20201002\" srcset=\"https://s0.wp.com/latex.php?latex=L%28w%2C+b%2C+%5Calpha%29+%3D+%5Cfrac%7B1%7D%7B2%7D+%28%5Csum_%7Bi%7D+%5Calpha_%7Bi%7D+y_%7Bi%7D+x_%7Bi%7D%29%28%5Csum_%7Bj%7D+%5Calpha_%7Bj%7D+y_%7Bj%7D+x_%7Bj%7D%29+-+%28%5Csum_%7Bi%7D%5Calpha_%7Bi%7D+y_%7Bi%7D+x_%7Bi%7D%29%28%5Csum_%7Bj%7D+%5Calpha_%7Bj%7D+y_%7Bj%7D+x_%7Bj%7D%29+-+%5Csum_%7Bi%7D+%5Calpha_%7Bi%7D+y_%7Bi%7D+%2B+%5Csum_%7Bi%7D+%5Calpha_%7Bi%7D\u0026#038;bg=ffffff\u0026#038;fg=000\u0026#038;s=0\u0026#038;c=20201002 1x, https://s0.wp.com/latex.php?latex=L%28w%2C+b%2C+%5Calpha%29+%3D+%5Cfrac%7B1%7D%7B2%7D+%28%5Csum_%7Bi%7D+%5Calpha_%7Bi%7D+y_%7Bi%7D+x_%7Bi%7D%29%28%5Csum_%7Bj%7D+%5Calpha_%7Bj%7D+y_%7Bj%7D+x_%7Bj%7D%29+-+%28%5Csum_%7Bi%7D%5Calpha_%7Bi%7D+y_%7Bi%7D+x_%7Bi%7D%29%28%5Csum_%7Bj%7D+%5Calpha_%7Bj%7D+y_%7Bj%7D+x_%7Bj%7D%29+-+%5Csum_%7Bi%7D+%5Calpha_%7Bi%7D+y_%7Bi%7D+%2B+%5Csum_%7Bi%7D+%5Calpha_%7Bi%7D\u0026#038;bg=ffffff\u0026#038;fg=000\u0026#038;s=0\u0026#038;c=20201002\u0026#038;zoom=4.5 4x\" alt=\"L(w, b, \u0026#92;alpha) = \u0026#92;frac{1}{2} (\u0026#92;sum_{i} \u0026#92;alpha_{i} y_{i} x_{i})(\u0026#92;sum_{j} \u0026#92;alpha_{j} y_{j} x_{j}) - (\u0026#92;sum_{i}\u0026#92;alpha_{i} y_{i} x_{i})(\u0026#92;sum_{j} \u0026#92;alpha_{j} y_{j} x_{j}) - \u0026#92;sum_{i} \u0026#92;alpha_{i} y_{i} + \u0026#92;sum_{i} \u0026#92;alpha_{i}\" class=\"latex\" /\u003e\u003c/p\u003e\n\u003cp style=\"text-align:left;\"\u003eSince the second last term equals zero, this becomes\u003c/p\u003e\n\u003cp style=\"text-align:center;\"\u003e\u003cimg src=\"https://s0.wp.com/latex.php?latex=L%28w%2C+b%2C+%5Calpha%29+%3D+%5Csum_%7Bi%7D+%5Calpha_%7Bi%7D+-+%5Cfrac%7B1%7D%7B2%7D+%5Csum_%7Bi%7D%5Csum_%7Bj%7D+%5Calpha_%7Bi%7D%5Calpha_%7Bj%7D%C2%A0y_%7Bi%7D+y_%7Bj%7D+x_%7Bi%7D+%5Ccdot+x_%7Bj%7D+%5Cquad+%285%29\u0026#038;bg=ffffff\u0026#038;fg=000\u0026#038;s=0\u0026#038;c=20201002\" srcset=\"https://s0.wp.com/latex.php?latex=L%28w%2C+b%2C+%5Calpha%29+%3D+%5Csum_%7Bi%7D+%5Calpha_%7Bi%7D+-+%5Cfrac%7B1%7D%7B2%7D+%5Csum_%7Bi%7D%5Csum_%7Bj%7D+%5Calpha_%7Bi%7D%5Calpha_%7Bj%7D%C2%A0y_%7Bi%7D+y_%7Bj%7D+x_%7Bi%7D+%5Ccdot+x_%7Bj%7D+%5Cquad+%285%29\u0026#038;bg=ffffff\u0026#038;fg=000\u0026#038;s=0\u0026#038;c=20201002 1x, https://s0.wp.com/latex.php?latex=L%28w%2C+b%2C+%5Calpha%29+%3D+%5Csum_%7Bi%7D+%5Calpha_%7Bi%7D+-+%5Cfrac%7B1%7D%7B2%7D+%5Csum_%7Bi%7D%5Csum_%7Bj%7D+%5Calpha_%7Bi%7D%5Calpha_%7Bj%7D%C2%A0y_%7Bi%7D+y_%7Bj%7D+x_%7Bi%7D+%5Ccdot+x_%7Bj%7D+%5Cquad+%285%29\u0026#038;bg=ffffff\u0026#038;fg=000\u0026#038;s=0\u0026#038;c=20201002\u0026#038;zoom=4.5 4x\" alt=\"L(w, b, \u0026#92;alpha) = \u0026#92;sum_{i} \u0026#92;alpha_{i} - \u0026#92;frac{1}{2} \u0026#92;sum_{i}\u0026#92;sum_{j} \u0026#92;alpha_{i}\u0026#92;alpha_{j} y_{i} y_{j} x_{i} \u0026#92;cdot x_{j} \u0026#92;quad (5)\" class=\"latex\" /\u003e\u003c/p\u003e\n\u003cp style=\"text-align:left;\"\u003eand this is the formula we want to maximize. We can see that the Lagrangian depends on samples dot product\u003c/p\u003e\n\u003cp style=\"text-align:center;\"\u003e\u003cimg src=\"https://s0.wp.com/latex.php?latex=x_%7Bi%7D+%5Ccdot+x_%7Bj%7D\u0026#038;bg=ffffff\u0026#038;fg=000\u0026#038;s=0\u0026#038;c=20201002\" srcset=\"https://s0.wp.com/latex.php?latex=x_%7Bi%7D+%5Ccdot+x_%7Bj%7D\u0026#038;bg=ffffff\u0026#038;fg=000\u0026#038;s=0\u0026#038;c=20201002 1x, https://s0.wp.com/latex.php?latex=x_%7Bi%7D+%5Ccdot+x_%7Bj%7D\u0026#038;bg=ffffff\u0026#038;fg=000\u0026#038;s=0\u0026#038;c=20201002\u0026#038;zoom=4.5 4x\" alt=\"x_{i} \u0026#92;cdot x_{j}\" class=\"latex\" /\u003e\u003c/p\u003e\n\u003cp\u003eNow substituting the vector w into (2) leads to\u003c/p\u003e\n\u003cp style=\"text-align:center;\"\u003e\u003cimg src=\"https://s0.wp.com/latex.php?latex=%5Csum_%7Bi%7D+%5Calpha_%7Bi%7D+y_%7Bi%7D+%5Ccdot+x_%7Bi%7D+%2B+b+%3D+0\u0026#038;bg=ffffff\u0026#038;fg=000\u0026#038;s=0\u0026#038;c=20201002\" srcset=\"https://s0.wp.com/latex.php?latex=%5Csum_%7Bi%7D+%5Calpha_%7Bi%7D+y_%7Bi%7D+%5Ccdot+x_%7Bi%7D+%2B+b+%3D+0\u0026#038;bg=ffffff\u0026#038;fg=000\u0026#038;s=0\u0026#038;c=20201002 1x, https://s0.wp.com/latex.php?latex=%5Csum_%7Bi%7D+%5Calpha_%7Bi%7D+y_%7Bi%7D+%5Ccdot+x_%7Bi%7D+%2B+b+%3D+0\u0026#038;bg=ffffff\u0026#038;fg=000\u0026#038;s=0\u0026#038;c=20201002\u0026#038;zoom=4.5 4x\" alt=\"\u0026#92;sum_{i} \u0026#92;alpha_{i} y_{i} \u0026#92;cdot x_{i} + b = 0\" class=\"latex\" /\u003e\u003c/p\u003e\n\u003cp style=\"text-align:left;\"\u003eWe have a total dependence on the dot products. Dot products tell us how alike features are. If \u003cimg src=\"https://s0.wp.com/latex.php?latex=x_%7Bi%7D%2C+x_%7Bj%7D\u0026#038;bg=ffffff\u0026#038;fg=000\u0026#038;s=0\u0026#038;c=20201002\" srcset=\"https://s0.wp.com/latex.php?latex=x_%7Bi%7D%2C+x_%7Bj%7D\u0026#038;bg=ffffff\u0026#038;fg=000\u0026#038;s=0\u0026#038;c=20201002 1x, https://s0.wp.com/latex.php?latex=x_%7Bi%7D%2C+x_%7Bj%7D\u0026#038;bg=ffffff\u0026#038;fg=000\u0026#038;s=0\u0026#038;c=20201002\u0026#038;zoom=4.5 4x\" alt=\"x_{i}, x_{j}\" class=\"latex\" /\u003e are similar, their dot product will be one and they will contribute to the correct answer. If the are not similar, their dot product will be zero and they will not contribute to the answer.\u003c/p\u003e\n\u003cp style=\"text-align:left;\"\u003eBut, what in the case when out data is not linearly separable? In that case, we can take a transformation which will take us from the space we are in, into a different space where we will be able to separate the data. Since maximization depends only on dot products, we can take the transformation of one vector, dotted with the transformation of another vector. The resulting function is called a Kernel function and we define it as\u003c/p\u003e\n\u003cp style=\"text-align:center;\"\u003e\u003cimg src=\"https://s0.wp.com/latex.php?latex=K%28x_%7Bi%7D%2C+x_%7Bj%7D%29+%3D+%5Cphi%28x_%7Bi%7D%29+%5Ccdot+%5Cphi%28x_%7Bj%7D%29\u0026#038;bg=ffffff\u0026#038;fg=000\u0026#038;s=0\u0026#038;c=20201002\" srcset=\"https://s0.wp.com/latex.php?latex=K%28x_%7Bi%7D%2C+x_%7Bj%7D%29+%3D+%5Cphi%28x_%7Bi%7D%29+%5Ccdot+%5Cphi%28x_%7Bj%7D%29\u0026#038;bg=ffffff\u0026#038;fg=000\u0026#038;s=0\u0026#038;c=20201002 1x, https://s0.wp.com/latex.php?latex=K%28x_%7Bi%7D%2C+x_%7Bj%7D%29+%3D+%5Cphi%28x_%7Bi%7D%29+%5Ccdot+%5Cphi%28x_%7Bj%7D%29\u0026#038;bg=ffffff\u0026#038;fg=000\u0026#038;s=0\u0026#038;c=20201002\u0026#038;zoom=4.5 4x\" alt=\"K(x_{i}, x_{j}) = \u0026#92;phi(x_{i}) \u0026#92;cdot \u0026#92;phi(x_{j})\" class=\"latex\" /\u003e\u003c/p\u003e\n\u003cp style=\"text-align:left;\"\u003ewhere\u003c/p\u003e\n\u003cp style=\"text-align:center;\"\u003e\u003cimg src=\"https://s0.wp.com/latex.php?latex=%5Cphi%28x_%7Bi%7D%29%2C+%5Cphi%28x_%7Bj%7D%29\u0026#038;bg=ffffff\u0026#038;fg=000\u0026#038;s=0\u0026#038;c=20201002\" srcset=\"https://s0.wp.com/latex.php?latex=%5Cphi%28x_%7Bi%7D%29%2C+%5Cphi%28x_%7Bj%7D%29\u0026#038;bg=ffffff\u0026#038;fg=000\u0026#038;s=0\u0026#038;c=20201002 1x, https://s0.wp.com/latex.php?latex=%5Cphi%28x_%7Bi%7D%29%2C+%5Cphi%28x_%7Bj%7D%29\u0026#038;bg=ffffff\u0026#038;fg=000\u0026#038;s=0\u0026#038;c=20201002\u0026#038;zoom=4.5 4x\" alt=\"\u0026#92;phi(x_{i}), \u0026#92;phi(x_{j})\" class=\"latex\" /\u003e\u003c/p\u003e\n\u003cp style=\"text-align:left;\"\u003eare vector transformations. Some commonly used kernel functions are linear, polynomial, and Gaussian kernels. Kernel functions are the reason why the SVM algorithms are so popular. If we have a data that is not linearly separable, we can apply a kernel function to it and transform it into a higher dimension in a way that is not computationally expensive. Then, in this higher dimension, we can linearly separate the data. This is usually called \u0026#8216;the kernel trick\u0026#8217;. Of course, there are constraints in which scenarios this is possible, but I won\u0026#8217;t be talking about that now.\u003c/p\u003e\n\u003cp style=\"text-align:left;\"\u003eNow let\u0026#8217;s switch to Python [1]. Suppose we have the following CSV file:\u003c/p\u003e\n\u003ctable border=\"0\" cellspacing=\"0\"\u003e\n\u003ccolgroup width=\"69\"\u003e\u003c/colgroup\u003e\n\u003ccolgroup width=\"55\"\u003e\u003c/colgroup\u003e\n\u003ccolgroup width=\"35\"\u003e\u003c/colgroup\u003e\n\u003ccolgroup width=\"110\"\u003e\u003c/colgroup\u003e\n\u003ccolgroup width=\"75\"\u003e\u003c/colgroup\u003e\n\u003ctbody\u003e\n\u003ctr\u003e\n\u003ctd align=\"left\" height=\"17\"\u003eUser ID\u003c/td\u003e\n\u003ctd align=\"left\"\u003eGender\u003c/td\u003e\n\u003ctd align=\"left\"\u003eAge\u003c/td\u003e\n\u003ctd align=\"left\"\u003eEstimatedSalary\u003c/td\u003e\n\u003ctd align=\"left\"\u003ePurchased\u003c/td\u003e\n\u003c/tr\u003e\n\u003ctr\u003e\n\u003ctd align=\"right\" height=\"17\"\u003e15624510\u003c/td\u003e\n\u003ctd align=\"left\"\u003eMale\u003c/td\u003e\n\u003ctd align=\"right\"\u003e19\u003c/td\u003e\n\u003ctd align=\"right\"\u003e19000\u003c/td\u003e\n\u003ctd align=\"right\"\u003e0\u003c/td\u003e\n\u003c/tr\u003e\n\u003ctr\u003e\n\u003ctd align=\"right\" height=\"17\"\u003e15810944\u003c/td\u003e\n\u003ctd align=\"left\"\u003eMale\u003c/td\u003e\n\u003ctd align=\"right\"\u003e35\u003c/td\u003e\n\u003ctd align=\"right\"\u003e20000\u003c/td\u003e\n\u003ctd align=\"right\"\u003e0\u003c/td\u003e\n\u003c/tr\u003e\n\u003ctr\u003e\n\u003ctd align=\"right\" height=\"17\"\u003e15668575\u003c/td\u003e\n\u003ctd align=\"left\"\u003eFemale\u003c/td\u003e\n\u003ctd align=\"right\"\u003e26\u003c/td\u003e\n\u003ctd align=\"right\"\u003e43000\u003c/td\u003e\n\u003ctd align=\"right\"\u003e0\u003c/td\u003e\n\u003c/tr\u003e\n\u003ctr\u003e\n\u003ctd align=\"right\" height=\"17\"\u003e15603246\u003c/td\u003e\n\u003ctd align=\"left\"\u003eFemale\u003c/td\u003e\n\u003ctd align=\"right\"\u003e27\u003c/td\u003e\n\u003ctd align=\"right\"\u003e57000\u003c/td\u003e\n\u003ctd align=\"right\"\u003e0\u003c/td\u003e\n\u003c/tr\u003e\n\u003ctr\u003e\n\u003ctd align=\"right\" height=\"17\"\u003e15804002\u003c/td\u003e\n\u003ctd align=\"left\"\u003eMale\u003c/td\u003e\n\u003ctd align=\"right\"\u003e19\u003c/td\u003e\n\u003ctd align=\"right\"\u003e76000\u003c/td\u003e\n\u003ctd align=\"right\"\u003e0\u003c/td\u003e\n\u003c/tr\u003e\n\u003ctr\u003e\n\u003ctd align=\"right\" height=\"17\"\u003e15728773\u003c/td\u003e\n\u003ctd align=\"left\"\u003eMale\u003c/td\u003e\n\u003ctd align=\"right\"\u003e27\u003c/td\u003e\n\u003ctd align=\"right\"\u003e58000\u003c/td\u003e\n\u003ctd align=\"right\"\u003e0\u003c/td\u003e\n\u003c/tr\u003e\n\u003ctr\u003e\n\u003ctd align=\"right\" height=\"17\"\u003e15598044\u003c/td\u003e\n\u003ctd align=\"left\"\u003eFemale\u003c/td\u003e\n\u003ctd align=\"right\"\u003e27\u003c/td\u003e\n\u003ctd align=\"right\"\u003e84000\u003c/td\u003e\n\u003ctd align=\"right\"\u003e0\u003c/td\u003e\n\u003c/tr\u003e\n\u003ctr\u003e\n\u003ctd align=\"right\" height=\"17\"\u003e15694829\u003c/td\u003e\n\u003ctd align=\"left\"\u003eFemale\u003c/td\u003e\n\u003ctd align=\"right\"\u003e32\u003c/td\u003e\n\u003ctd align=\"right\"\u003e150000\u003c/td\u003e\n\u003ctd align=\"right\"\u003e1\u003c/td\u003e\n\u003c/tr\u003e\n\u003ctr\u003e\n\u003ctd align=\"right\" height=\"17\"\u003e15600575\u003c/td\u003e\n\u003ctd align=\"left\"\u003eMale\u003c/td\u003e\n\u003ctd align=\"right\"\u003e25\u003c/td\u003e\n\u003ctd align=\"right\"\u003e33000\u003c/td\u003e\n\u003ctd align=\"right\"\u003e0\u003c/td\u003e\n\u003c/tr\u003e\n\u003ctr\u003e\n\u003ctd align=\"right\" height=\"17\"\u003e15727311\u003c/td\u003e\n\u003ctd align=\"left\"\u003eFemale\u003c/td\u003e\n\u003ctd align=\"right\"\u003e35\u003c/td\u003e\n\u003ctd align=\"right\"\u003e65000\u003c/td\u003e\n\u003ctd align=\"right\"\u003e0\u003c/td\u003e\n\u003c/tr\u003e\n\u003ctr\u003e\n\u003ctd align=\"right\" height=\"17\"\u003e15570769\u003c/td\u003e\n\u003ctd align=\"left\"\u003eFemale\u003c/td\u003e\n\u003ctd align=\"right\"\u003e26\u003c/td\u003e\n\u003ctd align=\"right\"\u003e80000\u003c/td\u003e\n\u003ctd align=\"right\"\u003e0\u003c/td\u003e\n\u003c/tr\u003e\n\u003ctr\u003e\n\u003ctd align=\"right\" height=\"17\"\u003e15606274\u003c/td\u003e\n\u003ctd align=\"left\"\u003eFemale\u003c/td\u003e\n\u003ctd align=\"right\"\u003e26\u003c/td\u003e\n\u003ctd align=\"right\"\u003e52000\u003c/td\u003e\n\u003ctd align=\"right\"\u003e0\u003c/td\u003e\n\u003c/tr\u003e\n\u003ctr\u003e\n\u003ctd align=\"right\" height=\"17\"\u003e15746139\u003c/td\u003e\n\u003ctd align=\"left\"\u003eMale\u003c/td\u003e\n\u003ctd align=\"right\"\u003e20\u003c/td\u003e\n\u003ctd align=\"right\"\u003e86000\u003c/td\u003e\n\u003ctd align=\"right\"\u003e0\u003c/td\u003e\n\u003c/tr\u003e\n\u003ctr\u003e\n\u003ctd align=\"right\" height=\"17\"\u003e15704987\u003c/td\u003e\n\u003ctd align=\"left\"\u003eMale\u003c/td\u003e\n\u003ctd align=\"right\"\u003e32\u003c/td\u003e\n\u003ctd align=\"right\"\u003e18000\u003c/td\u003e\n\u003ctd align=\"right\"\u003e0\u003c/td\u003e\n\u003c/tr\u003e\n\u003ctr\u003e\n\u003ctd align=\"right\" height=\"17\"\u003e15628972\u003c/td\u003e\n\u003ctd align=\"left\"\u003eMale\u003c/td\u003e\n\u003ctd align=\"right\"\u003e18\u003c/td\u003e\n\u003ctd align=\"right\"\u003e82000\u003c/td\u003e\n\u003ctd align=\"right\"\u003e0\u003c/td\u003e\n\u003c/tr\u003e\n\u003ctr\u003e\n\u003ctd align=\"right\" height=\"17\"\u003e15697686\u003c/td\u003e\n\u003ctd align=\"left\"\u003eMale\u003c/td\u003e\n\u003ctd align=\"right\"\u003e29\u003c/td\u003e\n\u003ctd align=\"right\"\u003e80000\u003c/td\u003e\n\u003ctd align=\"right\"\u003e0\u003c/td\u003e\n\u003c/tr\u003e\n\u003ctr\u003e\n\u003ctd align=\"right\" height=\"17\"\u003e15733883\u003c/td\u003e\n\u003ctd align=\"left\"\u003eMale\u003c/td\u003e\n\u003ctd align=\"right\"\u003e47\u003c/td\u003e\n\u003ctd align=\"right\"\u003e25000\u003c/td\u003e\n\u003ctd align=\"right\"\u003e1\u003c/td\u003e\n\u003c/tr\u003e\n\u003ctr\u003e\n\u003ctd align=\"right\" height=\"17\"\u003e15617482\u003c/td\u003e\n\u003ctd align=\"left\"\u003eMale\u003c/td\u003e\n\u003ctd align=\"right\"\u003e45\u003c/td\u003e\n\u003ctd align=\"right\"\u003e26000\u003c/td\u003e\n\u003ctd align=\"right\"\u003e1\u003c/td\u003e\n\u003c/tr\u003e\n\u003ctr\u003e\n\u003ctd align=\"right\" height=\"17\"\u003e15704583\u003c/td\u003e\n\u003ctd align=\"left\"\u003eMale\u003c/td\u003e\n\u003ctd align=\"right\"\u003e46\u003c/td\u003e\n\u003ctd align=\"right\"\u003e28000\u003c/td\u003e\n\u003ctd align=\"right\"\u003e1\u003c/td\u003e\n\u003c/tr\u003e\n\u003c/tbody\u003e\n\u003c/table\u003e\n\u003cp style=\"text-align:left;\"\u003eWe are trying to predict which users are going to make a purchase (buy the SUV car) according to their salary, gender, and age, and which users are not likely to buy it. As usual, we will first import some utility libraries that we are going to use.\u003c/p\u003e\n\u003cpre style=\"text-align:left;\"\u003eimport numpy as np\nimport matplotlib.pyplot as plt\nimport pandas as pd\u003c/pre\u003e\n\u003cp style=\"text-align:left;\"\u003eThen we need to import the dataset and split it into the training and test sets. Also, we need to do a feature scaling since the \u0026#8216;Estimated Salary\u0026#8217; and \u0026#8216;Age\u0026#8217; columns, for example, have different scales.\u003c/p\u003e\n\u003cpre style=\"text-align:left;\"\u003edataset = pd.read_csv('social_network_ads.csv')\nx = dataset.iloc[:, [2, 3]].values\ny = dataset.iloc[:, 4].values\n\nfrom sklearn.cross_validation import train_test_split\nx_train, x_test, y_train, y_test = train_test_split(X, y, test_size = 0.25, random_state = 0)\n\nfrom sklearn.preprocessing import StandardScaler\nsc = StandardScaler()\nx_train = sc.fit_transform(x_train)\nx_test = sc.transform(x_test)\u003c/pre\u003e\n\u003cp style=\"text-align:left;\"\u003eNow we are ready to start with the SVM. We will import svm library from sklearn and fit svm to the training set, using linear kernel function.\u003c/p\u003e\n\u003cpre style=\"text-align:left;\"\u003efrom sklearn.svm import SVC\nclassifier = SVC(kernel = 'linear', random_state = 0)\nclassifier.fit(x_train, y_train)\u003c/pre\u003e\n\u003cp style=\"text-align:left;\"\u003eThe next step is to predict the test set results.\u003c/p\u003e\n\u003cpre style=\"text-align:left;\"\u003ey_pred = classifier.predict(x_test)\u003c/pre\u003e\n\u003cp style=\"text-align:left;\"\u003eNow, all that is left to do is to visualize results. First, let\u0026#8217;s see how the training set looks like.\u003c/p\u003e\n\u003cpre style=\"text-align:left;\"\u003efrom matplotlib.colors import ListedColormap\nx_set, y_set = x_train, y_train\n\nX1, X2 = np.meshgrid(np.arange(start = X_set[:, 0].min() - 1, stop = X_set[:, 0].max() + 1, step = 0.01),\n                     np.arange(start = X_set[:, 1].min() - 1, stop = X_set[:, 1].max() + 1, step = 0.01))\n\nplt.contourf(X1, X2, classifier.predict(np.array([X1.ravel(), X2.ravel()]).T).reshape(X1.shape),\n             alpha = 0.75, cmap = ListedColormap(('red', 'green')))\nplt.xlim(X1.min(), X1.max())\nplt.ylim(X2.min(), X2.max())\n\nfor i, j in enumerate(np.unique(y_set)):\n  plt.scatter(X_set[y_set == j, 0], X_set[y_set == j, 1],\n              c = ListedColormap(('red', 'green'))(i), label = j)\nplt.title('SVM (Training set)')\nplt.xlabel('Age')\nplt.ylabel('Estimated Salary')\nplt.legend()\nplt.show()\u003c/pre\u003e\n\u003cp style=\"text-align:left;\"\u003eThis gives us the following picture\u003c/p\u003e\n\u003cp style=\"text-align:left;\"\u003e\u003cimg loading=\"lazy\" data-attachment-id=\"1587\" data-permalink=\"https://lucijagregov.com/2017/04/02/support-vector-machine-svm/svm-training/\" data-orig-file=\"https://lucijagregov.com/wp-content/uploads/2017/04/svm-training.png\" data-orig-size=\"575,453\" data-comments-opened=\"1\" data-image-meta=\"{\u0026quot;aperture\u0026quot;:\u0026quot;0\u0026quot;,\u0026quot;credit\u0026quot;:\u0026quot;\u0026quot;,\u0026quot;camera\u0026quot;:\u0026quot;\u0026quot;,\u0026quot;caption\u0026quot;:\u0026quot;\u0026quot;,\u0026quot;created_timestamp\u0026quot;:\u0026quot;0\u0026quot;,\u0026quot;copyright\u0026quot;:\u0026quot;\u0026quot;,\u0026quot;focal_length\u0026quot;:\u0026quot;0\u0026quot;,\u0026quot;iso\u0026quot;:\u0026quot;0\u0026quot;,\u0026quot;shutter_speed\u0026quot;:\u0026quot;0\u0026quot;,\u0026quot;title\u0026quot;:\u0026quot;\u0026quot;,\u0026quot;orientation\u0026quot;:\u0026quot;0\u0026quot;}\" data-image-title=\"svm-training\" data-image-description=\"\" data-image-caption=\"\" data-medium-file=\"https://lucijagregov.com/wp-content/uploads/2017/04/svm-training.png?w=300\" data-large-file=\"https://lucijagregov.com/wp-content/uploads/2017/04/svm-training.png?w=529\" class=\"alignnone size-full wp-image-1587\" src=\"https://lucijagregov.com/wp-content/uploads/2017/04/svm-training.png\" alt=\"svm-training\" width=\"575\" height=\"453\" srcset=\"https://lucijagregov.com/wp-content/uploads/2017/04/svm-training.png 575w, https://lucijagregov.com/wp-content/uploads/2017/04/svm-training.png?w=150\u0026amp;h=118 150w, https://lucijagregov.com/wp-content/uploads/2017/04/svm-training.png?w=300\u0026amp;h=236 300w\" sizes=\"(max-width: 575px) 100vw, 575px\" /\u003e\u003c/p\u003e\n\u003cp style=\"text-align:left;\"\u003eHere, points represent what really happened, whether the user purchased the SUV (green points), or not (red points). We also have green and red regions. Any user falling inside the red region is predicted not to buy the SUV, and similarly, any user falling inside the green region is predicted to buy the SUV. The separating curve between the regions is called the prediction boundary.\u003c/p\u003e\n\u003cp style=\"text-align:left;\"\u003eWe can see that predictions could be better. Green points around the point (1, -1) and green points around (-1, 2) ended up incorrectly inside the red region. The reason for this incorrect result is that we have chosen the linear kernel on a data which is not linearly separable.\u003c/p\u003e\n\u003cp style=\"text-align:left;\"\u003eAnd finally, the test set results will give us similar predictions.\u003c/p\u003e\n\u003cpre style=\"text-align:left;\"\u003efrom matplotlib.colors import ListedColormap\nx_set, y_set = x_test, y_test\n\nX1, X2 = np.meshgrid(np.arange(start = X_set[:, 0].min() - 1, stop = X_set[:, 0].max() + 1, step = 0.01),\n                     np.arange(start = X_set[:, 1].min() - 1, stop = X_set[:, 1].max() + 1, step = 0.01))\nplt.contourf(X1, X2, classifier.predict(np.array([X1.ravel(), X2.ravel()]).T).reshape(X1.shape),\n             alpha = 0.75, cmap = ListedColormap(('red', 'green')))\nplt.xlim(X1.min(), X1.max())\nplt.ylim(X2.min(), X2.max())\n\nfor i, j in enumerate(np.unique(y_set)):\n  plt.scatter(X_set[y_set == j, 0], X_set[y_set == j, 1],\n              c = ListedColormap(('red', 'green'))(i), label = j)\nplt.title('SVM (Test set)')\nplt.xlabel('Age')\nplt.ylabel('Estimated Salary')\nplt.legend()\nplt.show()\u003c/pre\u003e\n\u003cp style=\"text-align:left;\"\u003e\u003cimg loading=\"lazy\" data-attachment-id=\"1596\" data-permalink=\"https://lucijagregov.com/2017/04/02/support-vector-machine-svm/svm-test/\" data-orig-file=\"https://lucijagregov.com/wp-content/uploads/2017/04/svm-test.png\" data-orig-size=\"594,453\" data-comments-opened=\"1\" data-image-meta=\"{\u0026quot;aperture\u0026quot;:\u0026quot;0\u0026quot;,\u0026quot;credit\u0026quot;:\u0026quot;\u0026quot;,\u0026quot;camera\u0026quot;:\u0026quot;\u0026quot;,\u0026quot;caption\u0026quot;:\u0026quot;\u0026quot;,\u0026quot;created_timestamp\u0026quot;:\u0026quot;0\u0026quot;,\u0026quot;copyright\u0026quot;:\u0026quot;\u0026quot;,\u0026quot;focal_length\u0026quot;:\u0026quot;0\u0026quot;,\u0026quot;iso\u0026quot;:\u0026quot;0\u0026quot;,\u0026quot;shutter_speed\u0026quot;:\u0026quot;0\u0026quot;,\u0026quot;title\u0026quot;:\u0026quot;\u0026quot;,\u0026quot;orientation\u0026quot;:\u0026quot;0\u0026quot;}\" data-image-title=\"svm-test\" data-image-description=\"\" data-image-caption=\"\" data-medium-file=\"https://lucijagregov.com/wp-content/uploads/2017/04/svm-test.png?w=300\" data-large-file=\"https://lucijagregov.com/wp-content/uploads/2017/04/svm-test.png?w=529\" class=\"alignnone size-full wp-image-1596\" src=\"https://lucijagregov.com/wp-content/uploads/2017/04/svm-test.png\" alt=\"svm-test\" width=\"594\" height=\"453\" srcset=\"https://lucijagregov.com/wp-content/uploads/2017/04/svm-test.png 594w, https://lucijagregov.com/wp-content/uploads/2017/04/svm-test.png?w=150\u0026amp;h=114 150w, https://lucijagregov.com/wp-content/uploads/2017/04/svm-test.png?w=300\u0026amp;h=229 300w\" sizes=\"(max-width: 594px) 100vw, 594px\" /\u003e\u003c/p\u003e\n\u003cp style=\"text-align:left;\"\u003eThose predictions are also not so good because the linear kernel is unable to separate the data properly. How can we improve this? We can, of course, try a different kernel function which is more convenient for data which is not linearly separable. We can try this with a \u003ca href=\"https://en.wikipedia.org/wiki/Radial_basis_function_kernel\"\u003eGaussian radial basis function kernel\u003c/a\u003e (RBF)\u003c/p\u003e\n\u003cp style=\"text-align:center;\"\u003e\u003cimg src=\"https://s0.wp.com/latex.php?latex=K%28x%2C+x%5E%7B%5Cprime%7D%29+%3D+exp%28-+%5Cfrac%7B%5C%7Cx+-+x%5E%7B%5Cprime%7D%5C%7C%5E2%7D%7B2+%5Csigma%5E2%7D%29\u0026#038;bg=ffffff\u0026#038;fg=000\u0026#038;s=0\u0026#038;c=20201002\" srcset=\"https://s0.wp.com/latex.php?latex=K%28x%2C+x%5E%7B%5Cprime%7D%29+%3D+exp%28-+%5Cfrac%7B%5C%7Cx+-+x%5E%7B%5Cprime%7D%5C%7C%5E2%7D%7B2+%5Csigma%5E2%7D%29\u0026#038;bg=ffffff\u0026#038;fg=000\u0026#038;s=0\u0026#038;c=20201002 1x, https://s0.wp.com/latex.php?latex=K%28x%2C+x%5E%7B%5Cprime%7D%29+%3D+exp%28-+%5Cfrac%7B%5C%7Cx+-+x%5E%7B%5Cprime%7D%5C%7C%5E2%7D%7B2+%5Csigma%5E2%7D%29\u0026#038;bg=ffffff\u0026#038;fg=000\u0026#038;s=0\u0026#038;c=20201002\u0026#038;zoom=4.5 4x\" alt=\"K(x, x^{\u0026#92;prime}) = exp(- \u0026#92;frac{\u0026#92;|x - x^{\u0026#92;prime}\u0026#92;|^2}{2 \u0026#92;sigma^2})\" class=\"latex\" /\u003e\u003c/p\u003e\n\u003cp style=\"text-align:left;\"\u003ewhere\u003c/p\u003e\n\u003cp style=\"text-align:center;\"\u003e\u003cimg src=\"https://s0.wp.com/latex.php?latex=x%2C+x%5E%7B%5Cprime%7D\u0026#038;bg=ffffff\u0026#038;fg=000\u0026#038;s=0\u0026#038;c=20201002\" srcset=\"https://s0.wp.com/latex.php?latex=x%2C+x%5E%7B%5Cprime%7D\u0026#038;bg=ffffff\u0026#038;fg=000\u0026#038;s=0\u0026#038;c=20201002 1x, https://s0.wp.com/latex.php?latex=x%2C+x%5E%7B%5Cprime%7D\u0026#038;bg=ffffff\u0026#038;fg=000\u0026#038;s=0\u0026#038;c=20201002\u0026#038;zoom=4.5 4x\" alt=\"x, x^{\u0026#92;prime}\" class=\"latex\" /\u003e\u003c/p\u003e\n\u003cp style=\"text-align:left;\"\u003eare feature vectors and \u003cimg src=\"https://s0.wp.com/latex.php?latex=%5Csigma\u0026#038;bg=ffffff\u0026#038;fg=000\u0026#038;s=0\u0026#038;c=20201002\" srcset=\"https://s0.wp.com/latex.php?latex=%5Csigma\u0026#038;bg=ffffff\u0026#038;fg=000\u0026#038;s=0\u0026#038;c=20201002 1x, https://s0.wp.com/latex.php?latex=%5Csigma\u0026#038;bg=ffffff\u0026#038;fg=000\u0026#038;s=0\u0026#038;c=20201002\u0026#038;zoom=4.5 4x\" alt=\"\u0026#92;sigma\" class=\"latex\" /\u003e is a free parameter.\u003c/p\u003e\n\u003cp style=\"text-align:left;\"\u003eThe only thing that we need to change in our code above is the SVM classifier part. So, instead of a \u0026#8216;linear\u0026#8217; function, we will use the \u0026#8216;rbf\u0026#8217; function.\u003c/p\u003e\n\u003cpre style=\"text-align:left;\"\u003efrom sklearn.svm import SVC\nclassifier = SVC(kernel = 'rbf', random_state = 0)\nclassifier.fit(x_train, y_train)\u003c/pre\u003e\n\u003cp style=\"text-align:left;\"\u003eVisualization for the training set gives\u003c/p\u003e\n\u003cp style=\"text-align:left;\"\u003e\u003cimg loading=\"lazy\" data-attachment-id=\"1640\" data-permalink=\"https://lucijagregov.com/2017/04/02/support-vector-machine-svm/svm-kernel-training/\" data-orig-file=\"https://lucijagregov.com/wp-content/uploads/2017/04/svm-kernel-training.png\" data-orig-size=\"587,446\" data-comments-opened=\"1\" data-image-meta=\"{\u0026quot;aperture\u0026quot;:\u0026quot;0\u0026quot;,\u0026quot;credit\u0026quot;:\u0026quot;\u0026quot;,\u0026quot;camera\u0026quot;:\u0026quot;\u0026quot;,\u0026quot;caption\u0026quot;:\u0026quot;\u0026quot;,\u0026quot;created_timestamp\u0026quot;:\u0026quot;0\u0026quot;,\u0026quot;copyright\u0026quot;:\u0026quot;\u0026quot;,\u0026quot;focal_length\u0026quot;:\u0026quot;0\u0026quot;,\u0026quot;iso\u0026quot;:\u0026quot;0\u0026quot;,\u0026quot;shutter_speed\u0026quot;:\u0026quot;0\u0026quot;,\u0026quot;title\u0026quot;:\u0026quot;\u0026quot;,\u0026quot;orientation\u0026quot;:\u0026quot;0\u0026quot;}\" data-image-title=\"svm-kernel-training\" data-image-description=\"\" data-image-caption=\"\" data-medium-file=\"https://lucijagregov.com/wp-content/uploads/2017/04/svm-kernel-training.png?w=300\" data-large-file=\"https://lucijagregov.com/wp-content/uploads/2017/04/svm-kernel-training.png?w=529\" class=\"alignnone size-full wp-image-1640\" src=\"https://lucijagregov.com/wp-content/uploads/2017/04/svm-kernel-training.png\" alt=\"svm-kernel-training\" width=\"587\" height=\"446\" srcset=\"https://lucijagregov.com/wp-content/uploads/2017/04/svm-kernel-training.png 587w, https://lucijagregov.com/wp-content/uploads/2017/04/svm-kernel-training.png?w=150\u0026amp;h=114 150w, https://lucijagregov.com/wp-content/uploads/2017/04/svm-kernel-training.png?w=300\u0026amp;h=228 300w\" sizes=\"(max-width: 587px) 100vw, 587px\" /\u003e\u003c/p\u003e\n\u003cp style=\"text-align:left;\"\u003eWe can see that this is much better than in the case of the linear kernel function. Some of the green points in the middle are still inside the red region but that is still good because the SVM kernel is not overfitting data.\u003c/p\u003e\n\u003cp style=\"text-align:left;\"\u003eFor more information about this broad topic, please use the comment section or see resources below.\u003c/p\u003e\n\u003cp\u003eResources:\u003c/p\u003e\n\u003col\u003e\n\u003cli\u003e\u003ca href=\"https://www.udemy.com/machinelearning\" rel=\"nofollow\"\u003ehttps://www.udemy.com/machinelearning\u003c/a\u003e\u003c/li\u003e\n\u003cli\u003e\u003ca href=\"http://cs229.stanford.edu/notes/cs229-notes3.pdf\" rel=\"nofollow\"\u003ehttp://cs229.stanford.edu/notes/cs229-notes3.pdf\u003c/a\u003e\u003c/li\u003e\n\u003cli\u003e\u003ca href=\"http://www.robots.ox.ac.uk/~az/lectures/ml/lect2.pdf\" rel=\"nofollow\"\u003ehttp://www.robots.ox.ac.uk/~az/lectures/ml/lect2.pdf\u003c/a\u003e\u003c/li\u003e\n\u003cli\u003e\u003ca href=\"http://pages.cs.wisc.edu/~dyer/cs540/notes/10_svm.pdf\" rel=\"nofollow\"\u003ehttp://pages.cs.wisc.edu/~dyer/cs540/notes/10_svm.pdf\u003c/a\u003e\u003c/li\u003e\n\u003cli\u003e\u003ca href=\"https://www.youtube.com/watch?v=_PwhiWxHK8o\u0026#038;t=204s\" rel=\"nofollow\"\u003ehttps://www.youtube.com/watch?v=_PwhiWxHK8o\u0026#038;t=204s\u003c/a\u003e\u003c/li\u003e\n\u003cli\u003e\u003ca href=\"https://www.youtube.com/watch?v=eUfvyUEGMD8\" rel=\"nofollow\"\u003ehttps://www.youtube.com/watch?v=eUfvyUEGMD8\u003c/a\u003e\u003c/li\u003e\n\u003cli\u003e\u003ca href=\"http://www.deeplearningbook.org/contents/ml.html\" rel=\"nofollow\"\u003ehttp://www.deeplearningbook.org/contents/ml.html\u003c/a\u003e\u003c/li\u003e\n\u003c/ol\u003e\n",
      "summary": "Support Vector Machine is a supervised learning type of algorithm and its goal is to find the optimal hyperplane which \u0026#8230;\u003cp\u003e\u003ca href=\"https://lucijagregov.com/2017/04/02/support-vector-machine-svm/\"\u003eContinue reading \u003cspan class=\"meta-nav\"\u003e\u0026#8594;\u003c/span\u003e\u003c/a\u003e\u003c/p\u003e",
      "date_published": "2017-04-02T21:51:42Z",
      "authors": [
        {
          "name": "Lucija Gregov"
        }
      ],
      "tags": [
        "Career",
        "Development",
        "Tech",
        "Machine Learning",
        "Python"
      ],
      "_signal_feed_title": "Coffee and PI",
      "_signal_feed_url": "https://lucijagregov.com"
    }
  ],
  "_signal_generated": "2026-04-16T02:25:18Z",
  "_signal_period": "2017-04"
}